MANIFEST.in
README
setup.cfg
setup.py
setupegg.py
bin/pylocator
doc/Makefile
doc/__init__.py
doc/documentation.zip
doc/build/pylocator_20120419_10:58.zip
doc/build/pylocator_20120419_10:59.zip
doc/build/pylocator_20120419_12:08.zip
doc/build/pylocator_20120419_12:10.zip
doc/build/pylocator_20120419_15:49.zip
doc/build/pylocator_20120419_16:02.zip
doc/build/pylocator_20120419_16:04.zip
doc/build/pylocator_20120419_16:08.zip
doc/build/doctrees/environment.pickle
doc/build/doctrees/faq.doctree
doc/build/doctrees/index.doctree
doc/build/doctrees/install.doctree
doc/build/doctrees/tutorial.doctree
doc/build/html/.buildinfo
doc/build/html/faq.html
doc/build/html/genindex.html
doc/build/html/index.html
doc/build/html/install.html
doc/build/html/objects.inv
doc/build/html/search.html
doc/build/html/searchindex.js
doc/build/html/tutorial.html
doc/build/html/.doctrees/environment.pickle
doc/build/html/.doctrees/faq.doctree
doc/build/html/.doctrees/index.doctree
doc/build/html/.doctrees/install.doctree
doc/build/html/.doctrees/tutorial.doctree
doc/build/html/_images/faq_rois1.png
doc/build/html/_images/screen1.png
doc/build/html/_images/tutorial3.png
doc/build/html/_images/tutorial4.png
doc/build/html/_images/tutorial5.png
doc/build/html/_images/tutorial6.png
doc/build/html/_images/tutorial7.png
doc/build/html/_images/tutorial8.png
doc/build/html/_sources/faq.txt
doc/build/html/_sources/index.txt
doc/build/html/_sources/install.txt
doc/build/html/_sources/tutorial.txt
doc/build/html/_static/basic.css
doc/build/html/_static/default.css
doc/build/html/_static/doctools.js
doc/build/html/_static/faq_rois1.png
doc/build/html/_static/file.png
doc/build/html/_static/jquery.js
doc/build/html/_static/logo.png
doc/build/html/_static/logo1.png
doc/build/html/_static/logo2.bmp
doc/build/html/_static/logo2.png
doc/build/html/_static/minus.png
doc/build/html/_static/plus.png
doc/build/html/_static/pygments.css
doc/build/html/_static/pylocator.css
doc/build/html/_static/screen1.png
pylocator.egg-info/PKG-INFO
pylocator.egg-info/SOURCES.txt
pylocator.egg-info/dependency_links.txt
pylocator.egg-info/not-zip-safe
pylocator.egg-info/top_level.txt
