Metadata-Version: 1.0
Name: pylocator
Version: 1.0.beta.1.dev
Summary: 
